dasbus/__init__.py
dasbus/connection.py
dasbus/constants.py
dasbus/error.py
dasbus/identifier.py
dasbus/loop.py
dasbus/namespace.py
dasbus/signal.py
dasbus/specification.py
dasbus/structure.py
dasbus/typing.py
dasbus/xml.py
dasbus/client/__init__.py
dasbus/client/handler.py
dasbus/client/observer.py
dasbus/client/property.py
dasbus/client/proxy.py
dasbus/server/__init__.py
dasbus/server/container.py
dasbus/server/handler.py
dasbus/server/interface.py
dasbus/server/property.py
dasbus/server/publishable.py
dasbus/server/template.py
dasbus-1.6.dist-info/LICENSE
dasbus-1.6.dist-info/METADATA
dasbus-1.6.dist-info/WHEEL
dasbus-1.6.dist-info/top_level.txt
dasbus-1.6.dist-info/RECORD
