Metadata-Version: 2.1
Name: dasbus
Version: 1.6
Summary: DBus library in Python 3
Home-page: https://github.com/rhinstaller/dasbus
Author: Vendula Poncova
Author-email: vponcova@redhat.com
License: UNKNOWN
Keywords: dbus glib library
Platform: UNKNOWN
Classifier: Development Status :: 5 - Production/Stable
Classifier: Intended Audience :: Developers
Classifier: License :: OSI Approved :: GNU Lesser General Public License v2 or later (LGPLv2+)
Classifier: Programming Language :: Python :: 3
Requires-Python: >=3.6
